rng_jax.py
rng_jax-0.0.4.dist-info/METADATA
rng_jax-0.0.4.dist-info/WHEEL
rng_jax-0.0.4.dist-info/RECORD
