Metadata-Version: 2.4
Name: rng-jax
Version: 0.0.4
Summary: JAX random number generation as a NumPy generator
Project-URL: Repository, https://github.com/glass-dev/rng-jax
Project-URL: Issues, https://github.com/glass-dev/rng-jax
Author-email: Nicolas Tessore <n.tessore@ucl.ac.uk>
License-Expression: MIT
Classifier: License :: OSI Approved :: MIT License
Classifier: Operating System :: OS Independent
Classifier: Programming Language :: Python :: 3
Requires-Python: >=3.9
Requires-Dist: jax
Provides-Extra: doc
Requires-Dist: furo; extra == 'doc'
Requires-Dist: sphinx; extra == 'doc'
Provides-Extra: test
Requires-Dist: pytest; extra == 'test'
Requires-Dist: pytest-cov; extra == 'test'
